{"ap-northeast-1":{"windows-2019":{"name":"Windows_Server-2019-English-Full-Base-2021.10.13","creationDate":"2021-10-13T06:19:19.000Z","ami":"ami-0890484998c6a6e77"},"windows-2016":{"name":"Windows_Server-2016-English-Full-Base-2021.10.13","creationDate":"2021-10-13T06:37:00.000Z","ami":"ami-0c3ee428a3a16157e"},"ubuntu-18.04":{"name":"ubuntu/images/hvm-ssd/ubuntu-bionic-18.04-arm64-server-20210928","creationDate":"2021-09-28T21:13:19.000Z","ami":"ami-084fef42cc25bd43b"},"windows-2019-core":{"name":"Windows_Server-2019-English-Core-Base-2021.10.13","creationDate":"2021-10-13T05:19:28.000Z","ami":"ami-05888176121c3c67f"},"ubuntu-16.04":{"name":"ubuntu/images/hvm-ssd/ubuntu-xenial-16.04-arm64-server-20210928","creationDate":"2021-09-29T16:45:55.000Z","ami":"ami-06602ea953ba135a9"},"ubuntu-20.04":{"name":"ubuntu/images/hvm-ssd/ubuntu-focal-20.04-arm64-server-20211021","creationDate":"2021-10-22T00:40:36.000Z","ami":"ami-0e61b583d5d7356b8"},"windows-2016-core":{"name":"Windows_Server-2016-English-Core-Base-2021.10.13","creationDate":"2021-10-13T05:35:57.000Z","ami":"ami-0d048bdd5b1f80734"}},"ap-northeast-2":{"windows-2019":{"name":"Windows_Server-2019-English-Full-Base-2021.10.13","creationDate":"2021-10-13T06:19:20.000Z","ami":"ami-081e530f100d962be"},"windows-2016":{"name":"Windows_Server-2016-English-Full-Base-2021.10.13","creationDate":"2021-10-13T06:37:00.000Z","ami":"ami-0dbf4cf107bda9144"},"ubuntu-18.04":{"name":"ubuntu/images/hvm-ssd/ubuntu-bionic-18.04-arm64-server-20210928","creationDate":"2021-09-28T21:13:22.000Z","ami":"ami-0951e7086d4f429e3"},"windows-2019-core":{"name":"Windows_Server-2019-English-Core-Base-2021.10.13","creationDate":"2021-10-13T05:19:30.000Z","ami":"ami-026b4498d5ffe8cb9"},"ubuntu-16.04":{"name":"ubuntu/images/hvm-ssd/ubuntu-xenial-16.04-arm64-server-20210928","creationDate":"2021-09-29T16:45:58.000Z","ami":"ami-0b37e6563ef42a0eb"},"ubuntu-20.04":{"name":"ubuntu/images/hvm-ssd/ubuntu-focal-20.04-arm64-server-20211021","creationDate":"2021-10-22T00:40:39.000Z","ami":"ami-00e9c733a0bb11ca4"},"windows-2016-core":{"name":"Windows_Server-2016-English-Core-Base-2021.10.13","creationDate":"2021-10-13T05:35:57.000Z","ami":"ami-06873b53abdfec99c"}},"ap-northeast-3":{"windows-2019":{"name":"Windows_Server-2019-English-Full-Base-2021.10.13","creationDate":"2021-10-13T06:19:20.000Z","ami":"ami-0ce3798fb9f5c9883"},"windows-2016":{"name":"Windows_Server-2016-English-Full-Base-2021.10.13","creationDate":"2021-10-13T06:37:01.000Z","ami":"ami-0deef74b1239f69bd"},"ubuntu-18.04":{"name":"ubuntu/images/hvm-ssd/ubuntu-bionic-18.04-arm64-server-20210928","creationDate":"2021-09-28T21:13:26.000Z","ami":"ami-0d7e0af5cc66c5658"},"windows-2019-core":{"name":"Windows_Server-2019-English-Core-Base-2021.10.13","creationDate":"2021-10-13T05:19:30.000Z","ami":"ami-0714696e542ea0ce0"},"ubuntu-16.04":{"name":"ubuntu/images/hvm-ssd/ubuntu-xenial-16.04-arm64-server-20210928","creationDate":"2021-09-29T16:46:00.000Z","ami":"ami-0ab5b86f9b84122c8"},"ubuntu-20.04":{"name":"ubuntu/images/hvm-ssd/ubuntu-focal-20.04-arm64-server-20211021","creationDate":"2021-10-22T00:40:41.000Z","ami":"ami-01ed8c3fcbc024c37"},"windows-2016-core":{"name":"Windows_Server-2016-English-Core-Base-2021.10.13","creationDate":"2021-10-13T05:35:58.000Z","ami":"ami-0ba58b24dcb3e28dd"}},"ap-south-1":{"windows-2019":{"name":"Windows_Server-2019-English-Full-Base-2021.10.13","creationDate":"2021-10-13T06:19:23.000Z","ami":"ami-0e7d76dfc4fac48d6"},"windows-2016":{"name":"Windows_Server-2016-English-Full-Base-2021.10.13","creationDate":"2021-10-13T06:37:04.000Z","ami":"ami-09e99ecc6126d3d36"},"ubuntu-18.04":{"name":"ubuntu/images/hvm-ssd/ubuntu-bionic-18.04-arm64-server-20210928","creationDate":"2021-09-28T21:13:29.000Z","ami":"ami-0015f172ae811cb38"},"windows-2019-core":{"name":"Windows_Server-2019-English-Core-Base-2021.10.13","creationDate":"2021-10-13T05:19:33.000Z","ami":"ami-0307978f05c3d63c0"},"ubuntu-16.04":{"name":"ubuntu/images/hvm-ssd/ubuntu-xenial-16.04-arm64-server-20210928","creationDate":"2021-09-29T16:46:02.000Z","ami":"ami-0ae12517fe595ce17"},"ubuntu-20.04":{"name":"ubuntu/images/hvm-ssd/ubuntu-focal-20.04-arm64-server-20211021","creationDate":"2021-10-22T00:40:43.000Z","ami":"ami-08198662331cf1a51"},"windows-2016-core":{"name":"Windows_Server-2016-English-Core-Base-2021.10.13","creationDate":"2021-10-13T05:36:01.000Z","ami":"ami-08decbfbdc0e7ce17"}},"ap-southeast-1":{"windows-2019":{"name":"Windows_Server-2019-English-Full-Base-2021.10.13","creationDate":"2021-10-13T06:19:18.000Z","ami":"ami-0bd2beaddfd6419fc"},"windows-2016":{"name":"Windows_Server-2016-English-Full-Base-2021.10.13","creationDate":"2021-10-13T06:36:58.000Z","ami":"ami-06acd7cbe65da0fde"},"ubuntu-18.04":{"name":"ubuntu/images/hvm-ssd/ubuntu-bionic-18.04-arm64-server-20210928","creationDate":"2021-09-28T21:13:31.000Z","ami":"ami-08fbc9ee9a141eb29"},"windows-2019-core":{"name":"Windows_Server-2019-English-Core-Base-2021.10.13","creationDate":"2021-10-13T05:19:26.000Z","ami":"ami-01233570102433058"},"ubuntu-16.04":{"name":"ubuntu/images/hvm-ssd/ubuntu-xenial-16.04-arm64-server-20210928","creationDate":"2021-09-29T16:46:04.000Z","ami":"ami-03b6c12f592f54cf3"},"ubuntu-20.04":{"name":"ubuntu/images/hvm-ssd/ubuntu-focal-20.04-arm64-server-20211021","creationDate":"2021-10-22T00:40:45.000Z","ami":"ami-030dafd151929100f"},"windows-2016-core":{"name":"Windows_Server-2016-English-Core-Base-2021.10.13","creationDate":"2021-10-13T05:35:56.000Z","ami":"ami-08ce8d4d19d348f74"}},"ap-southeast-2":{"windows-2019":{"name":"Windows_Server-2019-English-Full-Base-2021.10.13","creationDate":"2021-10-13T06:19:19.000Z","ami":"ami-00803a3c61ac12ee2"},"windows-2016":{"name":"Windows_Server-2016-English-Full-Base-2021.10.13","creationDate":"2021-10-13T06:36:59.000Z","ami":"ami-04632b5664be92c83"},"ubuntu-18.04":{"name":"ubuntu/images/hvm-ssd/ubuntu-bionic-18.04-arm64-server-20210928","creationDate":"2021-09-28T21:13:34.000Z","ami":"ami-0a64f062c3e702cf0"},"windows-2019-core":{"name":"Windows_Server-2019-English-Core-Base-2021.10.13","creationDate":"2021-10-13T05:19:27.000Z","ami":"ami-04a3d2ab8e2cb581b"},"ubuntu-16.04":{"name":"ubuntu/images/hvm-ssd/ubuntu-xenial-16.04-arm64-server-20210928","creationDate":"2021-09-29T16:46:08.000Z","ami":"ami-09fe2be72ca884906"},"ubuntu-20.04":{"name":"ubuntu/images/hvm-ssd/ubuntu-focal-20.04-arm64-server-20211021","creationDate":"2021-10-22T00:40:48.000Z","ami":"ami-02389157cb8d3e3b5"},"windows-2016-core":{"name":"Windows_Server-2016-English-Core-Base-2021.10.13","creationDate":"2021-10-13T05:35:57.000Z","ami":"ami-03f29166e9e1b60e9"}},"ca-central-1":{"windows-2019":{"name":"Windows_Server-2019-English-Full-Base-2021.10.13","creationDate":"2021-10-13T06:19:22.000Z","ami":"ami-04ce2d3d06e88b4cf"},"windows-2016":{"name":"Windows_Server-2016-English-Full-Base-2021.10.13","creationDate":"2021-10-13T06:37:03.000Z","ami":"ami-0ee702f865929fa4d"},"ubuntu-18.04":{"name":"ubuntu/images/hvm-ssd/ubuntu-bionic-18.04-arm64-server-20210928","creationDate":"2021-09-28T21:13:36.000Z","ami":"ami-096a6df1192f6a221"},"windows-2019-core":{"name":"Windows_Server-2019-English-Core-Base-2021.10.13","creationDate":"2021-10-13T05:19:33.000Z","ami":"ami-00be4aac78d75f669"},"ubuntu-16.04":{"name":"ubuntu/images/hvm-ssd/ubuntu-xenial-16.04-arm64-server-20210928","creationDate":"2021-09-29T16:46:09.000Z","ami":"ami-03fc4d6b3ea7e9081"},"ubuntu-20.04":{"name":"ubuntu/images/hvm-ssd/ubuntu-focal-20.04-arm64-server-20211021","creationDate":"2021-10-22T00:40:49.000Z","ami":"ami-0ed6506b456ca3729"},"windows-2016-core":{"name":"Windows_Server-2016-English-Core-Base-2021.10.13","creationDate":"2021-10-13T05:36:00.000Z","ami":"ami-0fb066ab77b53b625"}},"eu-central-1":{"windows-2019":{"name":"Windows_Server-2019-English-Full-Base-2021.10.13","creationDate":"2021-10-13T06:19:20.000Z","ami":"ami-06e9b42a08895adf6"},"windows-2016":{"name":"Windows_Server-2016-English-Full-Base-2021.10.13","creationDate":"2021-10-13T06:37:01.000Z","ami":"ami-0ba923521b4643446"},"ubuntu-18.04":{"name":"ubuntu/images/hvm-ssd/ubuntu-bionic-18.04-arm64-server-20210928","creationDate":"2021-09-28T21:13:37.000Z","ami":"ami-0fcb8c41ae8982f48"},"windows-2019-core":{"name":"Windows_Server-2019-English-Core-Base-2021.10.13","creationDate":"2021-10-13T05:19:31.000Z","ami":"ami-043d7e91e65598582"},"ubuntu-16.04":{"name":"ubuntu/images/hvm-ssd/ubuntu-xenial-16.04-arm64-server-20210928","creationDate":"2021-09-29T16:46:10.000Z","ami":"ami-074bcbbba36789937"},"ubuntu-20.04":{"name":"ubuntu/images/hvm-ssd/ubuntu-focal-20.04-arm64-server-20211021","creationDate":"2021-10-22T00:40:50.000Z","ami":"ami-0b4b0a5bd04aec558"},"windows-2016-core":{"name":"Windows_Server-2016-English-Core-Base-2021.10.13","creationDate":"2021-10-13T05:35:59.000Z","ami":"ami-037f0c149d6cc5340"}},"eu-north-1":{"windows-2019":{"name":"Windows_Server-2019-English-Full-Base-2021.10.13","creationDate":"2021-10-13T06:19:25.000Z","ami":"ami-07bce40826a463d1c"},"windows-2016":{"name":"Windows_Server-2016-English-Full-Base-2021.10.13","creationDate":"2021-10-13T06:37:06.000Z","ami":"ami-0ca0755da511f18df"},"ubuntu-18.04":{"name":"ubuntu/images/hvm-ssd/ubuntu-bionic-18.04-arm64-server-20210928","creationDate":"2021-09-28T21:13:37.000Z","ami":"ami-045a2fd051ffcaaa1"},"windows-2019-core":{"name":"Windows_Server-2019-English-Core-Base-2021.10.13","creationDate":"2021-10-13T05:19:36.000Z","ami":"ami-08c1e942a956a9df5"},"ubuntu-16.04":{"name":"ubuntu/images/hvm-ssd/ubuntu-xenial-16.04-arm64-server-20210928","creationDate":"2021-09-29T16:46:12.000Z","ami":"ami-083ac04a8442d4b7f"},"ubuntu-20.04":{"name":"ubuntu/images/hvm-ssd/ubuntu-focal-20.04-arm64-server-20211021","creationDate":"2021-10-22T00:40:51.000Z","ami":"ami-01cf7e0f481ff30b4"},"windows-2016-core":{"name":"Windows_Server-2016-English-Core-Base-2021.10.13","creationDate":"2021-10-13T05:36:05.000Z","ami":"ami-0482c5d122507409f"}},"eu-west-1":{"windows-2019":{"name":"Windows_Server-2019-English-Full-Base-2021.10.13","creationDate":"2021-10-13T06:19:15.000Z","ami":"ami-06938675032090695"},"windows-2016":{"name":"Windows_Server-2016-English-Full-Base-2021.10.13","creationDate":"2021-10-13T06:36:55.000Z","ami":"ami-0eb1f6b718af5946f"},"ubuntu-18.04":{"name":"ubuntu/images/hvm-ssd/ubuntu-bionic-18.04-arm64-server-20210928","creationDate":"2021-09-28T21:13:39.000Z","ami":"ami-07ad83602e11d983b"},"windows-2019-core":{"name":"Windows_Server-2019-English-Core-Base-2021.10.13","creationDate":"2021-10-13T05:19:24.000Z","ami":"ami-0e999e9a58ad619ae"},"ubuntu-16.04":{"name":"ubuntu/images/hvm-ssd/ubuntu-xenial-16.04-arm64-server-20210928","creationDate":"2021-09-29T16:46:14.000Z","ami":"ami-0e8225827581c983a"},"ubuntu-20.04":{"name":"ubuntu/images/hvm-ssd/ubuntu-focal-20.04-arm64-server-20211021","creationDate":"2021-10-22T00:40:52.000Z","ami":"ami-0f617e4136f03b9ad"},"windows-2016-core":{"name":"Windows_Server-2016-English-Core-Base-2021.10.13","creationDate":"2021-10-13T05:35:54.000Z","ami":"ami-0f0957307e2ce435a"}},"eu-west-2":{"windows-2019":{"name":"Windows_Server-2019-English-Full-Base-2021.10.13","creationDate":"2021-10-13T06:19:22.000Z","ami":"ami-0f9853ca76d115e7b"},"windows-2016":{"name":"Windows_Server-2016-English-Full-Base-2021.10.13","creationDate":"2021-10-13T06:37:04.000Z","ami":"ami-071214cf78c0d441c"},"ubuntu-18.04":{"name":"ubuntu/images/hvm-ssd/ubuntu-bionic-18.04-arm64-server-20210928","creationDate":"2021-09-28T21:13:39.000Z","ami":"ami-00455b9581676d8d0"},"windows-2019-core":{"name":"Windows_Server-2019-English-Core-Base-2021.10.13","creationDate":"2021-10-13T05:19:35.000Z","ami":"ami-05fb6512fd696d7dc"},"ubuntu-16.04":{"name":"ubuntu/images/hvm-ssd/ubuntu-xenial-16.04-arm64-server-20210928","creationDate":"2021-09-29T16:46:18.000Z","ami":"ami-01c0540df77ccaa68"},"ubuntu-20.04":{"name":"ubuntu/images/hvm-ssd/ubuntu-focal-20.04-arm64-server-20211021","creationDate":"2021-10-22T00:40:53.000Z","ami":"ami-0d21c64d5074a949a"},"windows-2016-core":{"name":"Windows_Server-2016-English-Core-Base-2021.10.13","creationDate":"2021-10-13T05:36:02.000Z","ami":"ami-053ceb8015ffc8a41"}},"eu-west-3":{"windows-2019":{"name":"Windows_Server-2019-English-Full-Base-2021.10.13","creationDate":"2021-10-13T06:19:23.000Z","ami":"ami-0c9ff4cc1d0291f62"},"windows-2016":{"name":"Windows_Server-2016-English-Full-Base-2021.10.13","creationDate":"2021-10-13T06:37:06.000Z","ami":"ami-0f5e9f39b535bddd5"},"ubuntu-18.04":{"name":"ubuntu/images/hvm-ssd/ubuntu-bionic-18.04-arm64-server-20210928","creationDate":"2021-09-28T21:13:40.000Z","ami":"ami-02b146a6b04335f83"},"windows-2019-core":{"name":"Windows_Server-2019-English-Core-Base-2021.10.13","creationDate":"2021-10-13T05:19:36.000Z","ami":"ami-0b7f803ec5d6a55ae"},"ubuntu-16.04":{"name":"ubuntu/images/hvm-ssd/ubuntu-xenial-16.04-arm64-server-20210928","creationDate":"2021-09-29T16:46:19.000Z","ami":"ami-0a5ee67e16e2e3530"},"ubuntu-20.04":{"name":"ubuntu/images/hvm-ssd/ubuntu-focal-20.04-arm64-server-20211021","creationDate":"2021-10-22T00:40:53.000Z","ami":"ami-0ac5e0f91c73c50f6"},"windows-2016-core":{"name":"Windows_Server-2016-English-Core-Base-2021.10.13","creationDate":"2021-10-13T05:36:03.000Z","ami":"ami-07d638dac6e81f46c"}},"sa-east-1":{"windows-2019":{"name":"Windows_Server-2019-English-Full-Base-2021.10.13","creationDate":"2021-10-13T06:19:20.000Z","ami":"ami-06ab8fe950abb04f5"},"windows-2016":{"name":"Windows_Server-2016-English-Full-Base-2021.10.13","creationDate":"2021-10-13T06:37:00.000Z","ami":"ami-05ee0993eea8dadad"},"ubuntu-18.04":{"name":"ubuntu/images/hvm-ssd/ubuntu-bionic-18.04-arm64-server-20210928","creationDate":"2021-09-28T21:13:43.000Z","ami":"ami-088b4ba257a07b063"},"windows-2019-core":{"name":"Windows_Server-2019-English-Core-Base-2021.10.13","creationDate":"2021-10-13T05:19:31.000Z","ami":"ami-0fb7456534b144a2d"},"ubuntu-16.04":{"name":"ubuntu/images/hvm-ssd/ubuntu-xenial-16.04-arm64-server-20210928","creationDate":"2021-09-29T16:46:29.000Z","ami":"ami-08bf1084c0b9a3361"},"ubuntu-20.04":{"name":"ubuntu/images/hvm-ssd/ubuntu-focal-20.04-arm64-server-20211021","creationDate":"2021-10-22T00:40:56.000Z","ami":"ami-04a5b8dd2ee07bb23"},"windows-2016-core":{"name":"Windows_Server-2016-English-Core-Base-2021.10.13","creationDate":"2021-10-13T05:35:58.000Z","ami":"ami-0ae997288c0128035"}},"us-east-1":{"windows-2019":{"name":"Windows_Server-2019-English-Full-Base-2021.10.13","creationDate":"2021-10-13T05:35:44.000Z","ami":"ami-0416f96ae3d1a3f29"},"windows-2016":{"name":"Windows_Server-2016-English-Full-Base-2021.10.13","creationDate":"2021-10-13T06:20:38.000Z","ami":"ami-01b1af98c9c81c8cd"},"ubuntu-18.04":{"name":"ubuntu/images/hvm-ssd/ubuntu-bionic-18.04-arm64-server-20210928","creationDate":"2021-09-28T21:13:45.000Z","ami":"ami-0a1960e00a6cb2f40"},"windows-2019-core":{"name":"Windows_Server-2019-English-Core-Base-2021.10.13","creationDate":"2021-10-13T05:04:29.000Z","ami":"ami-08a71d63d26fba64a"},"ubuntu-16.04":{"name":"ubuntu/images/hvm-ssd/ubuntu-xenial-16.04-arm64-server-20210928","creationDate":"2021-09-29T16:46:30.000Z","ami":"ami-04b3c39a8a1c62b76"},"ubuntu-20.04":{"name":"ubuntu/images/hvm-ssd/ubuntu-focal-20.04-arm64-server-20211021","creationDate":"2021-10-22T00:40:58.000Z","ami":"ami-04fe9398b2a27a600"},"windows-2016-core":{"name":"Windows_Server-2016-English-Core-Base-2021.10.13","creationDate":"2021-10-13T05:20:39.000Z","ami":"ami-051a7f87c573517bf"}},"us-east-2":{"windows-2019":{"name":"Windows_Server-2019-English-Full-Base-2021.10.13","creationDate":"2021-10-13T06:19:20.000Z","ami":"ami-08c213ebdf7b857c2"},"windows-2016":{"name":"Windows_Server-2016-English-Full-Base-2021.10.13","creationDate":"2021-10-13T06:37:03.000Z","ami":"ami-0e4f22bcdb62d60f8"},"ubuntu-18.04":{"name":"ubuntu/images/hvm-ssd/ubuntu-bionic-18.04-arm64-server-20210928","creationDate":"2021-09-28T21:13:46.000Z","ami":"ami-091f8c1b1fc845770"},"windows-2019-core":{"name":"Windows_Server-2019-English-Core-Base-2021.10.13","creationDate":"2021-10-13T05:19:32.000Z","ami":"ami-01c0d25ca9f3f64be"},"ubuntu-16.04":{"name":"ubuntu/images/hvm-ssd/ubuntu-xenial-16.04-arm64-server-20210928","creationDate":"2021-09-29T16:46:32.000Z","ami":"ami-0b76100074ce446d4"},"ubuntu-20.04":{"name":"ubuntu/images/hvm-ssd/ubuntu-focal-20.04-arm64-server-20211021","creationDate":"2021-10-22T00:40:59.000Z","ami":"ami-03b47d2d727e13114"},"windows-2016-core":{"name":"Windows_Server-2016-English-Core-Base-2021.10.13","creationDate":"2021-10-13T05:36:00.000Z","ami":"ami-0bd333394cf92f823"}},"us-west-1":{"windows-2019":{"name":"Windows_Server-2019-English-Full-Base-2021.10.13","creationDate":"2021-10-13T06:19:14.000Z","ami":"ami-0cf4a2d03d1a3d62c"},"windows-2016":{"name":"Windows_Server-2016-English-Full-Base-2021.10.13","creationDate":"2021-10-13T06:36:53.000Z","ami":"ami-0033fb419ec2059cb"},"ubuntu-18.04":{"name":"ubuntu/images/hvm-ssd/ubuntu-bionic-18.04-arm64-server-20210928","creationDate":"2021-09-28T21:13:49.000Z","ami":"ami-048ae5e032c396125"},"windows-2019-core":{"name":"Windows_Server-2019-English-Core-Base-2021.10.13","creationDate":"2021-10-13T05:19:23.000Z","ami":"ami-091e3f8a82d5aa672"},"ubuntu-16.04":{"name":"ubuntu/images/hvm-ssd/ubuntu-xenial-16.04-arm64-server-20210928","creationDate":"2021-09-29T16:46:33.000Z","ami":"ami-06d79d5316d395362"},"ubuntu-20.04":{"name":"ubuntu/images/hvm-ssd/ubuntu-focal-20.04-arm64-server-20211021","creationDate":"2021-10-22T00:41:00.000Z","ami":"ami-0de625cc489c46bfb"},"windows-2016-core":{"name":"Windows_Server-2016-English-Core-Base-2021.10.13","creationDate":"2021-10-13T05:35:51.000Z","ami":"ami-083a27fc2389bfa3d"}},"us-west-2":{"windows-2019":{"name":"Windows_Server-2019-English-Full-Base-2021.10.13","creationDate":"2021-10-13T06:19:16.000Z","ami":"ami-058b12f51d412b5db"},"windows-2016":{"name":"Windows_Server-2016-English-Full-Base-2021.10.13","creationDate":"2021-10-13T06:36:54.000Z","ami":"ami-00134213c3ad76118"},"ubuntu-18.04":{"name":"ubuntu/images/hvm-ssd/ubuntu-bionic-18.04-arm64-server-20210928","creationDate":"2021-09-28T21:13:50.000Z","ami":"ami-0c37f403328da60da"},"windows-2019-core":{"name":"Windows_Server-2019-English-Core-Base-2021.10.13","creationDate":"2021-10-13T05:19:24.000Z","ami":"ami-08a161f5180e8df56"},"ubuntu-16.04":{"name":"ubuntu/images/hvm-ssd/ubuntu-xenial-16.04-arm64-server-20210928","creationDate":"2021-09-29T16:46:35.000Z","ami":"ami-08305dd8ab642ad8c"},"ubuntu-20.04":{"name":"ubuntu/images/hvm-ssd/ubuntu-focal-20.04-arm64-server-20211021","creationDate":"2021-10-22T00:41:02.000Z","ami":"ami-017d56f5127a80893"},"windows-2016-core":{"name":"Windows_Server-2016-English-Core-Base-2021.10.13","creationDate":"2021-10-13T05:35:53.000Z","ami":"ami-02838c2ccda5c8fa4"}}}
