{"ap-northeast-1":{"windows-2016-core":{"creationDate":"2020-12-09T08:12:42.000Z","name":"Windows_Server-2016-English-Core-Base-2020.12.09","ami":"ami-039c332e3251cb1d6"},"windows-2019-core":{"creationDate":"2020-12-09T08:01:15.000Z","name":"Windows_Server-2019-English-Core-Base-2020.12.09","ami":"ami-032cf006fbe5edb0f"},"windows-2019":{"creationDate":"2020-12-09T10:31:29.000Z","name":"Windows_Server-2019-English-Full-Base-2020.12.09","ami":"ami-014612c2d9afaf1ac"},"ubuntu-16.04":{"creationDate":"2020-12-11T10:59:48.000Z","name":"ubuntu/images/hvm-ssd/ubuntu-xenial-16.04-amd64-server-20201210","ami":"ami-0af17d43b1f4ff4ea"},"ubuntu-20.04":{"creationDate":"2020-12-11T00:24:40.000Z","name":"ubuntu/images/hvm-ssd/ubuntu-focal-20.04-arm64-server-20201210","ami":"ami-0b3fc06997cbf3ee3"},"ubuntu-18.04":{"creationDate":"2020-12-11T12:58:31.000Z","name":"ubuntu/images/hvm-ssd/ubuntu-bionic-18.04-arm64-server-20201211.1","ami":"ami-0d0f264523c937c9e"},"windows-2016":{"creationDate":"2020-12-09T08:54:37.000Z","name":"Windows_Server-2016-English-Full-Base-2020.12.09","ami":"ami-0532b5a8a610e78e0"}},"ap-northeast-2":{"windows-2016-core":{"creationDate":"2020-12-09T08:12:43.000Z","name":"Windows_Server-2016-English-Core-Base-2020.12.09","ami":"ami-0cec6fd4de42bf65a"},"windows-2019-core":{"creationDate":"2020-12-09T08:01:16.000Z","name":"Windows_Server-2019-English-Core-Base-2020.12.09","ami":"ami-00ccc84b5e58d2508"},"windows-2019":{"creationDate":"2020-12-09T10:31:30.000Z","name":"Windows_Server-2019-English-Full-Base-2020.12.09","ami":"ami-02e14cbf0d1fa141a"},"ubuntu-16.04":{"creationDate":"2020-12-11T11:00:15.000Z","name":"ubuntu/images/hvm-ssd/ubuntu-xenial-16.04-amd64-server-20201210","ami":"ami-04e6fcf8cfe3b09ea"},"ubuntu-20.04":{"creationDate":"2020-12-11T00:25:08.000Z","name":"ubuntu/images/hvm-ssd/ubuntu-focal-20.04-arm64-server-20201210","ami":"ami-028864a795d09ec6b"},"ubuntu-18.04":{"creationDate":"2020-12-11T12:58:58.000Z","name":"ubuntu/images/hvm-ssd/ubuntu-bionic-18.04-arm64-server-20201211.1","ami":"ami-031d5c8d4f20ed725"},"windows-2016":{"creationDate":"2020-12-09T08:54:38.000Z","name":"Windows_Server-2016-English-Full-Base-2020.12.09","ami":"ami-03a54e0befb85b169"}},"ap-south-1":{"windows-2016-core":{"creationDate":"2020-12-09T08:12:46.000Z","name":"Windows_Server-2016-English-Core-Base-2020.12.09","ami":"ami-05d95f3c3077ecc9d"},"windows-2019-core":{"creationDate":"2020-12-09T08:01:20.000Z","name":"Windows_Server-2019-English-Core-Base-2020.12.09","ami":"ami-0b3db6fe221a68992"},"windows-2019":{"creationDate":"2020-12-09T10:31:33.000Z","name":"Windows_Server-2019-English-Full-Base-2020.12.09","ami":"ami-0c7b2e7fd5f6b0210"},"ubuntu-16.04":{"creationDate":"2020-12-11T11:00:20.000Z","name":"ubuntu/images/hvm-ssd/ubuntu-xenial-16.04-amd64-server-20201210","ami":"ami-0fd48e51ec5606ac1"},"ubuntu-20.04":{"creationDate":"2020-12-11T00:25:13.000Z","name":"ubuntu/images/hvm-ssd/ubuntu-focal-20.04-arm64-server-20201210","ami":"ami-0dadda4908404e3d6"},"ubuntu-18.04":{"creationDate":"2020-12-11T12:59:05.000Z","name":"ubuntu/images/hvm-ssd/ubuntu-bionic-18.04-arm64-server-20201211.1","ami":"ami-0636a0d305a4e0e42"},"windows-2016":{"creationDate":"2020-12-09T08:54:41.000Z","name":"Windows_Server-2016-English-Full-Base-2020.12.09","ami":"ami-08e6159a9ddcd3af8"}},"ap-southeast-1":{"windows-2016-core":{"creationDate":"2020-12-09T08:12:41.000Z","name":"Windows_Server-2016-English-Core-Base-2020.12.09","ami":"ami-043693ebfa4e21932"},"windows-2019-core":{"creationDate":"2020-12-09T08:01:14.000Z","name":"Windows_Server-2019-English-Core-Base-2020.12.09","ami":"ami-06688a855693f5a4d"},"windows-2019":{"creationDate":"2020-12-09T10:31:28.000Z","name":"Windows_Server-2019-English-Full-Base-2020.12.09","ami":"ami-0ea1b666a75da32ca"},"ubuntu-16.04":{"creationDate":"2020-12-11T11:00:11.000Z","name":"ubuntu/images/hvm-ssd/ubuntu-xenial-16.04-amd64-server-20201210","ami":"ami-0ba45f1ec3dff60f9"},"ubuntu-20.04":{"creationDate":"2020-12-11T00:25:03.000Z","name":"ubuntu/images/hvm-ssd/ubuntu-focal-20.04-arm64-server-20201210","ami":"ami-04271917f0eb1fbac"},"ubuntu-18.04":{"creationDate":"2020-12-11T12:58:55.000Z","name":"ubuntu/images/hvm-ssd/ubuntu-bionic-18.04-arm64-server-20201211.1","ami":"ami-0870c741c75006fd5"},"windows-2016":{"creationDate":"2020-12-09T08:54:37.000Z","name":"Windows_Server-2016-English-Full-Base-2020.12.09","ami":"ami-0507af8ed5331d76c"}},"ap-southeast-2":{"windows-2016-core":{"creationDate":"2020-12-09T08:12:41.000Z","name":"Windows_Server-2016-English-Core-Base-2020.12.09","ami":"ami-0be59ec6ada573666"},"windows-2019-core":{"creationDate":"2020-12-09T08:01:15.000Z","name":"Windows_Server-2019-English-Core-Base-2020.12.09","ami":"ami-09482a7c761c2bd68"},"windows-2019":{"creationDate":"2020-12-09T10:31:29.000Z","name":"Windows_Server-2019-English-Full-Base-2020.12.09","ami":"ami-019736e5600bb3b3f"},"ubuntu-16.04":{"creationDate":"2020-12-11T10:59:51.000Z","name":"ubuntu/images/hvm-ssd/ubuntu-xenial-16.04-amd64-server-20201210","ami":"ami-004d0fb87d10716c6"},"ubuntu-20.04":{"creationDate":"2020-12-11T00:24:44.000Z","name":"ubuntu/images/hvm-ssd/ubuntu-focal-20.04-arm64-server-20201210","ami":"ami-009fd4f79d8389897"},"ubuntu-18.04":{"creationDate":"2020-12-11T12:58:35.000Z","name":"ubuntu/images/hvm-ssd/ubuntu-bionic-18.04-arm64-server-20201211.1","ami":"ami-0293d45121893a1f8"},"windows-2016":{"creationDate":"2020-12-09T08:54:37.000Z","name":"Windows_Server-2016-English-Full-Base-2020.12.09","ami":"ami-0bb0102969354103e"}},"ca-central-1":{"windows-2016-core":{"creationDate":"2020-12-09T08:12:45.000Z","name":"Windows_Server-2016-English-Core-Base-2020.12.09","ami":"ami-0defd6035d11da62b"},"windows-2019-core":{"creationDate":"2020-12-09T08:01:18.000Z","name":"Windows_Server-2019-English-Core-Base-2020.12.09","ami":"ami-09d7e2b1a78c73dcc"},"windows-2019":{"creationDate":"2020-12-09T10:31:33.000Z","name":"Windows_Server-2019-English-Full-Base-2020.12.09","ami":"ami-0cdfa905439f4b9ca"},"ubuntu-16.04":{"creationDate":"2020-12-11T11:00:13.000Z","name":"ubuntu/images/hvm-ssd/ubuntu-xenial-16.04-amd64-server-20201210","ami":"ami-0033df0038e42d496"},"ubuntu-20.04":{"creationDate":"2020-12-11T00:25:05.000Z","name":"ubuntu/images/hvm-ssd/ubuntu-focal-20.04-arm64-server-20201210","ami":"ami-0e721fb1ed4609f80"},"ubuntu-18.04":{"creationDate":"2020-12-11T12:58:56.000Z","name":"ubuntu/images/hvm-ssd/ubuntu-bionic-18.04-arm64-server-20201211.1","ami":"ami-03304dee597638ce3"},"windows-2016":{"creationDate":"2020-12-09T08:54:41.000Z","name":"Windows_Server-2016-English-Full-Base-2020.12.09","ami":"ami-04999a2f2a757a768"}},"eu-central-1":{"windows-2016-core":{"creationDate":"2020-12-09T08:12:44.000Z","name":"Windows_Server-2016-English-Core-Base-2020.12.09","ami":"ami-0734a0c5dcf9af53c"},"windows-2019-core":{"creationDate":"2020-12-09T08:01:17.000Z","name":"Windows_Server-2019-English-Core-Base-2020.12.09","ami":"ami-0423924ae8bb61b73"},"windows-2019":{"creationDate":"2020-12-09T10:31:30.000Z","name":"Windows_Server-2019-English-Full-Base-2020.12.09","ami":"ami-01b65a06ec09db85c"},"ubuntu-16.04":{"creationDate":"2020-12-11T11:00:21.000Z","name":"ubuntu/images/hvm-ssd/ubuntu-xenial-16.04-amd64-server-20201210","ami":"ami-08a1a61694dd1c82f"},"ubuntu-20.04":{"creationDate":"2020-12-11T00:25:14.000Z","name":"ubuntu/images/hvm-ssd/ubuntu-focal-20.04-arm64-server-20201210","ami":"ami-024c9d46d0580c973"},"ubuntu-18.04":{"creationDate":"2020-12-11T12:59:05.000Z","name":"ubuntu/images/hvm-ssd/ubuntu-bionic-18.04-arm64-server-20201211.1","ami":"ami-012a1645d69193043"},"windows-2016":{"creationDate":"2020-12-09T08:54:39.000Z","name":"Windows_Server-2016-English-Full-Base-2020.12.09","ami":"ami-0117475ff9322fb3e"}},"eu-north-1":{"windows-2016-core":{"creationDate":"2020-12-09T08:12:49.000Z","name":"Windows_Server-2016-English-Core-Base-2020.12.09","ami":"ami-0aec02b7f4c94eebf"},"windows-2019-core":{"creationDate":"2020-12-09T08:01:20.000Z","name":"Windows_Server-2019-English-Core-Base-2020.12.09","ami":"ami-028635166a60524a2"},"windows-2019":{"creationDate":"2020-12-09T10:31:36.000Z","name":"Windows_Server-2019-English-Full-Base-2020.12.09","ami":"ami-079582353f0c5e97a"},"ubuntu-16.04":{"creationDate":"2020-12-11T11:00:18.000Z","name":"ubuntu/images/hvm-ssd/ubuntu-xenial-16.04-amd64-server-20201210","ami":"ami-0b8a39c91526d3e31"},"ubuntu-20.04":{"creationDate":"2020-12-11T00:25:11.000Z","name":"ubuntu/images/hvm-ssd/ubuntu-focal-20.04-arm64-server-20201210","ami":"ami-01cc468a52670a189"},"ubuntu-18.04":{"creationDate":"2020-12-11T12:59:01.000Z","name":"ubuntu/images/hvm-ssd/ubuntu-bionic-18.04-arm64-server-20201211.1","ami":"ami-091b361f53f4d3c59"},"windows-2016":{"creationDate":"2020-12-09T08:54:44.000Z","name":"Windows_Server-2016-English-Full-Base-2020.12.09","ami":"ami-0878daf17c69890eb"}},"eu-west-1":{"windows-2016-core":{"creationDate":"2020-12-09T08:12:38.000Z","name":"Windows_Server-2016-English-Core-Base-2020.12.09","ami":"ami-05f5a6b762fddf8d5"},"windows-2019-core":{"creationDate":"2020-12-09T08:01:13.000Z","name":"Windows_Server-2019-English-Core-Base-2020.12.09","ami":"ami-0c9f1487290af637d"},"windows-2019":{"creationDate":"2020-12-09T10:31:26.000Z","name":"Windows_Server-2019-English-Full-Base-2020.12.09","ami":"ami-0c95efaa8fa6e2424"},"ubuntu-16.04":{"creationDate":"2020-12-11T11:00:22.000Z","name":"ubuntu/images/hvm-ssd/ubuntu-xenial-16.04-amd64-server-20201210","ami":"ami-0d67111dcacb4a14a"},"ubuntu-20.04":{"creationDate":"2020-12-11T00:25:15.000Z","name":"ubuntu/images/hvm-ssd/ubuntu-focal-20.04-arm64-server-20201210","ami":"ami-026ca4cffbcd7f873"},"ubuntu-18.04":{"creationDate":"2020-12-11T12:59:06.000Z","name":"ubuntu/images/hvm-ssd/ubuntu-bionic-18.04-arm64-server-20201211.1","ami":"ami-0881231b822c824fd"},"windows-2016":{"creationDate":"2020-12-09T08:54:35.000Z","name":"Windows_Server-2016-English-Full-Base-2020.12.09","ami":"ami-07d8c98607d0b1326"}},"eu-west-2":{"windows-2016-core":{"creationDate":"2020-12-09T08:12:48.000Z","name":"Windows_Server-2016-English-Core-Base-2020.12.09","ami":"ami-0587b1b0ee4325c63"},"windows-2019-core":{"creationDate":"2020-12-09T08:01:19.000Z","name":"Windows_Server-2019-English-Core-Base-2020.12.09","ami":"ami-0ace8de2e4d72d675"},"windows-2019":{"creationDate":"2020-12-09T10:31:35.000Z","name":"Windows_Server-2019-English-Full-Base-2020.12.09","ami":"ami-01819d85044afd4c6"},"ubuntu-16.04":{"creationDate":"2020-12-11T11:00:23.000Z","name":"ubuntu/images/hvm-ssd/ubuntu-xenial-16.04-amd64-server-20201210","ami":"ami-03441ec6f2faa7ddc"},"ubuntu-20.04":{"creationDate":"2020-12-11T00:25:15.000Z","name":"ubuntu/images/hvm-ssd/ubuntu-focal-20.04-arm64-server-20201210","ami":"ami-06f2b69d88ac3580b"},"ubuntu-18.04":{"creationDate":"2020-12-11T12:59:07.000Z","name":"ubuntu/images/hvm-ssd/ubuntu-bionic-18.04-arm64-server-20201211.1","ami":"ami-00f6c7d250a48202f"},"windows-2016":{"creationDate":"2020-12-09T08:54:43.000Z","name":"Windows_Server-2016-English-Full-Base-2020.12.09","ami":"ami-01d3a5f3a7758eb94"}},"eu-west-3":{"windows-2016-core":{"creationDate":"2020-12-09T08:12:48.000Z","name":"Windows_Server-2016-English-Core-Base-2020.12.09","ami":"ami-0d2dac7dde5639ec6"},"windows-2019-core":{"creationDate":"2020-12-09T08:01:19.000Z","name":"Windows_Server-2019-English-Core-Base-2020.12.09","ami":"ami-0194141235f179ff2"},"windows-2019":{"creationDate":"2020-12-09T10:31:36.000Z","name":"Windows_Server-2019-English-Full-Base-2020.12.09","ami":"ami-03c0b6eae63b5a75c"},"ubuntu-16.04":{"creationDate":"2020-12-11T11:00:23.000Z","name":"ubuntu/images/hvm-ssd/ubuntu-xenial-16.04-amd64-server-20201210","ami":"ami-089971569f60f6120"},"ubuntu-20.04":{"creationDate":"2020-12-11T00:25:16.000Z","name":"ubuntu/images/hvm-ssd/ubuntu-focal-20.04-arm64-server-20201210","ami":"ami-0f8a17916620b16f3"},"ubuntu-18.04":{"creationDate":"2020-12-11T12:59:08.000Z","name":"ubuntu/images/hvm-ssd/ubuntu-bionic-18.04-arm64-server-20201211.1","ami":"ami-03abb1770e53d7397"},"windows-2016":{"creationDate":"2020-12-09T08:54:43.000Z","name":"Windows_Server-2016-English-Full-Base-2020.12.09","ami":"ami-09e51cb880e38038d"}},"sa-east-1":{"windows-2016-core":{"creationDate":"2020-12-09T08:12:51.000Z","name":"Windows_Server-2016-English-Core-Base-2020.12.09","ami":"ami-053944cf552df22e8"},"windows-2019-core":{"creationDate":"2020-12-09T08:01:23.000Z","name":"Windows_Server-2019-English-Core-Base-2020.12.09","ami":"ami-0970208b3665f7498"},"windows-2019":{"creationDate":"2020-12-09T10:31:37.000Z","name":"Windows_Server-2019-English-Full-Base-2020.12.09","ami":"ami-0378a9d5ce02e41c5"},"ubuntu-16.04":{"creationDate":"2020-12-11T11:00:07.000Z","name":"ubuntu/images/hvm-ssd/ubuntu-xenial-16.04-amd64-server-20201210","ami":"ami-0fca8261840464a30"},"ubuntu-20.04":{"creationDate":"2020-12-11T00:24:59.000Z","name":"ubuntu/images/hvm-ssd/ubuntu-focal-20.04-arm64-server-20201210","ami":"ami-0eae77e421116405b"},"ubuntu-18.04":{"creationDate":"2020-12-11T12:58:50.000Z","name":"ubuntu/images/hvm-ssd/ubuntu-bionic-18.04-arm64-server-20201211.1","ami":"ami-044f00ec822b87df5"},"windows-2016":{"creationDate":"2020-12-09T08:54:45.000Z","name":"Windows_Server-2016-English-Full-Base-2020.12.09","ami":"ami-04a40ca057345c1df"}},"us-east-1":{"windows-2016-core":{"creationDate":"2020-12-09T07:35:32.000Z","name":"Windows_Server-2016-English-Core-Base-2020.12.09","ami":"ami-084ee6b6607532182"},"windows-2019-core":{"creationDate":"2020-12-09T07:24:29.000Z","name":"Windows_Server-2019-English-Core-Base-2020.12.09","ami":"ami-075a1740f4844172a"},"windows-2019":{"creationDate":"2020-12-09T09:54:08.000Z","name":"Windows_Server-2019-English-Full-Base-2020.12.09","ami":"ami-0229f7666f517b31e"},"ubuntu-16.04":{"creationDate":"2020-12-11T10:59:34.000Z","name":"ubuntu/images/hvm-ssd/ubuntu-xenial-16.04-amd64-server-20201210","ami":"ami-099e921e69356cf89"},"ubuntu-20.04":{"creationDate":"2020-12-11T00:24:26.000Z","name":"ubuntu/images/hvm-ssd/ubuntu-focal-20.04-arm64-server-20201210","ami":"ami-061202d63ee650371"},"ubuntu-18.04":{"creationDate":"2020-12-11T12:58:16.000Z","name":"ubuntu/images/hvm-ssd/ubuntu-bionic-18.04-arm64-server-20201211.1","ami":"ami-012418b10d1e47fa5"},"windows-2016":{"creationDate":"2020-12-09T08:16:18.000Z","name":"Windows_Server-2016-English-Full-Base-2020.12.09","ami":"ami-0088977e66ac3915d"}},"us-east-2":{"windows-2016-core":{"creationDate":"2020-12-09T08:12:45.000Z","name":"Windows_Server-2016-English-Core-Base-2020.12.09","ami":"ami-0a3e46f7ca0d6e5df"},"windows-2019-core":{"creationDate":"2020-12-09T08:01:18.000Z","name":"Windows_Server-2019-English-Core-Base-2020.12.09","ami":"ami-0b2a4ac0d70ffcb45"},"windows-2019":{"creationDate":"2020-12-09T10:31:31.000Z","name":"Windows_Server-2019-English-Full-Base-2020.12.09","ami":"ami-0d5b55fd8cd8738f5"},"ubuntu-16.04":{"creationDate":"2020-12-11T11:00:09.000Z","name":"ubuntu/images/hvm-ssd/ubuntu-xenial-16.04-amd64-server-20201210","ami":"ami-05edbb8e25e281608"},"ubuntu-20.04":{"creationDate":"2020-12-11T00:25:01.000Z","name":"ubuntu/images/hvm-ssd/ubuntu-focal-20.04-arm64-server-20201210","ami":"ami-0a8251430bac13e68"},"ubuntu-18.04":{"creationDate":"2020-12-11T12:58:52.000Z","name":"ubuntu/images/hvm-ssd/ubuntu-bionic-18.04-arm64-server-20201211.1","ami":"ami-02fd94254301714d0"},"windows-2016":{"creationDate":"2020-12-09T08:54:41.000Z","name":"Windows_Server-2016-English-Full-Base-2020.12.09","ami":"ami-07e4bc48db918b14f"}},"us-west-1":{"windows-2016-core":{"creationDate":"2020-12-09T08:12:36.000Z","name":"Windows_Server-2016-English-Core-Base-2020.12.09","ami":"ami-08262d1ec08f6c505"},"windows-2019-core":{"creationDate":"2020-12-09T08:01:12.000Z","name":"Windows_Server-2019-English-Core-Base-2020.12.09","ami":"ami-06c16cea823cee5df"},"windows-2019":{"creationDate":"2020-12-09T10:31:24.000Z","name":"Windows_Server-2019-English-Full-Base-2020.12.09","ami":"ami-0ae930fa924b34ed3"},"ubuntu-16.04":{"creationDate":"2020-12-11T10:59:37.000Z","name":"ubuntu/images/hvm-ssd/ubuntu-xenial-16.04-amd64-server-20201210","ami":"ami-027fb6336945ac7f3"},"ubuntu-20.04":{"creationDate":"2020-12-11T00:24:29.000Z","name":"ubuntu/images/hvm-ssd/ubuntu-focal-20.04-arm64-server-20201210","ami":"ami-0fd5c97e74dafd86d"},"ubuntu-18.04":{"creationDate":"2020-12-11T12:58:20.000Z","name":"ubuntu/images/hvm-ssd/ubuntu-bionic-18.04-arm64-server-20201211.1","ami":"ami-0a8e680f0d0873e2d"},"windows-2016":{"creationDate":"2020-12-09T08:54:33.000Z","name":"Windows_Server-2016-English-Full-Base-2020.12.09","ami":"ami-0682ee0499b100d5e"}},"us-west-2":{"windows-2016-core":{"creationDate":"2020-12-09T08:12:37.000Z","name":"Windows_Server-2016-English-Core-Base-2020.12.09","ami":"ami-0f3f4568ef2b0bb8f"},"windows-2019-core":{"creationDate":"2020-12-09T08:01:12.000Z","name":"Windows_Server-2019-English-Core-Base-2020.12.09","ami":"ami-0ab9cfb8adcb95db4"},"windows-2019":{"creationDate":"2020-12-09T10:31:25.000Z","name":"Windows_Server-2019-English-Full-Base-2020.12.09","ami":"ami-0706901be27b0d22b"},"ubuntu-16.04":{"creationDate":"2020-12-11T11:00:17.000Z","name":"ubuntu/images/hvm-ssd/ubuntu-xenial-16.04-amd64-server-20201210","ami":"ami-00f1e37d20049f858"},"ubuntu-20.04":{"creationDate":"2020-12-11T00:25:10.000Z","name":"ubuntu/images/hvm-ssd/ubuntu-focal-20.04-arm64-server-20201210","ami":"ami-04c20ec241d42ae4c"},"ubuntu-18.04":{"creationDate":"2020-12-11T12:59:00.000Z","name":"ubuntu/images/hvm-ssd/ubuntu-bionic-18.04-arm64-server-20201211.1","ami":"ami-07be6cf8f458f18a8"},"windows-2016":{"creationDate":"2020-12-09T08:54:33.000Z","name":"Windows_Server-2016-English-Full-Base-2020.12.09","ami":"ami-07280e820068b6fff"}}}
